brainstack/__init__.py
brainstack/cli.py
brainstack/main.py
brainstack/controller/__init__.py
brainstack/controller/integrator_simple.py
brainstack/controller/router_rules.py
brainstack/modules/__init__.py
brainstack/modules/chaotic/__init__.py
brainstack/modules/chaotic/amplifier.py
brainstack/modules/embeddings/__init__.py
brainstack/modules/embeddings/image_embedder.py
brainstack/modules/embeddings/text_embedder.py
brainstack/modules/memory_classical/__init__.py
brainstack/modules/memory_classical/retriever.py
brainstack/modules/memory_classical/store.py
brainstack/modules/text/__init__.py
brainstack/modules/text/qa_small.py
brainstack/modules/vision/__init__.py
brainstack/modules/vision/vision_labeler.py
brainstack/utils/__init__.py
brainstack/utils/io.py
brainstack/utils/log.py
brainstack/utils/timing.py
brainstack-0.0.1.dist-info/licenses/LICENSE
brainstack-0.0.1.dist-info/METADATA
brainstack-0.0.1.dist-info/WHEEL
brainstack-0.0.1.dist-info/entry_points.txt
brainstack-0.0.1.dist-info/top_level.txt
brainstack-0.0.1.dist-info/RECORD
