Metadata-Version: 2.4
Name: brainstack
Version: 0.0.1
Summary: A CPU-friendly, modular mini-brain with explainable routing and tiny experts.
Author: Abhinav Basu
License: MIT
Requires-Python: >=3.12
License-File: LICENSE
Requires-Dist: numpy>=1.26
Requires-Dist: scikit-learn>=1.3
Requires-Dist: scipy>=1.11
Requires-Dist: rank-bm25>=0.2.2
Requires-Dist: nltk>=3.8
Requires-Dist: opencv-python>=4.9
Requires-Dist: pillow>=10.0
Requires-Dist: pyyaml>=6.0
Requires-Dist: tqdm>=4.66
Requires-Dist: pytest>=8.0
Dynamic: license-file
